tkmilan/__init__.py
tkmilan/__main__.py
tkmilan/autolayout.py
tkmilan/bg.py
tkmilan/diagram.py
tkmilan/drender.py
tkmilan/exception.py
tkmilan/fn.py
tkmilan/mixin.py
tkmilan/model.py
tkmilan/parser.py
tkmilan/py.typed
tkmilan/util.py
tkmilan/validation.py
tkmilan/var.py
tkmilan/showcase-images/README.md
tkmilan/showcase-images/error-s16.png
tkmilan/showcase-images/info-msgbox-s16.png
tkmilan/showcase-images/info-s16.png
tkmilan/showcase-images/warning-s16.png
tkmilan-0.61.dist-info/LICENSE
tkmilan-0.61.dist-info/METADATA
tkmilan-0.61.dist-info/WHEEL
tkmilan-0.61.dist-info/entry_points.txt
tkmilan-0.61.dist-info/top_level.txt
tkmilan-0.61.dist-info/RECORD
