Metadata-Version: 2.1
Name: tkmilan
Version: 0.61
Summary: tkinter's evil twin
Home-page: https://support.powertools-tech.com/PowertoolsTech/tkmilan
Author: Powertools Technologies
Author-email: simao.afonso@powertools-tech.com
Classifier: Development Status :: 3 - Alpha
Classifier: Programming Language :: Python :: 3 :: Only
Classifier: Intended Audience :: Developers
Classifier: License :: OSI Approved :: GNU Lesser General Public License v3 or later (LGPLv3+)
Requires-Python: >=3.8
License-File: LICENSE
Provides-Extra: images
Requires-Dist: PIL; extra == "images"
